<annotation>
  <folder>input</folder>
  <filename>images - 2020-02-11T193133.435.jpg</filename>
  <path>E:\Personal_Files\Code\Yolo-Training-GoogleColab\data_converstion\main\input\images - 2020-02-11T193133.435.jpg</path>
  <source>
    <database>Unknown</database>
  </source>
  <size>
    <width>180</width>
    <height>179</height>
    <depth>3</depth>
  </size>
  <segmented>0</segmented>
  <object>
    <name>gun</name>
    <pose>Unspecified</pose>
    <truncated>0</truncated>
    <difficult>0</difficult>
    <bndbox>
      <xmin>2</xmin>
      <ymin>1</ymin>
      <xmax>179</xmax>
      <ymax>178</ymax>
    </bndbox>
  </object>
</annotation>
